{"otherData": {},"traceEvents":[{"cat":"function","dur":296049,"name":"DeviceResources(HWND hWnd, int height, int width)","ph":"X","pid":0,"tid":816438708,"ts":1236569206125},{"cat":"function","dur":17124,"name":"void sandbox::LandAndWavesSceneCS::LoadTextures()","ph":"X","pid":0,"tid":816438708,"ts":1236569510972},{"cat":"function","dur":106021,"name":"void sandbox::LandAndWavesSceneCS::BuildLandAndWaterScene()","ph":"X","pid":0,"tid":816438708,"ts":1236569528114},{"cat":"function","dur":134069,"name":"LandAndWavesSceneCS()","ph":"X","pid":0,"tid":816438708,"ts":1236569502341},{"cat":"function","dur":430386,"name":"Sandbox Constructor","ph":"X","pid":0,"tid":816438708,"ts":1236569206072}]}